{"word": "absent", "type": "adj.", "meanings": [{"meaning": "", "collocation": [{"format": "VERBS", "groups": [{"words": ["be"], "examples": []}, {"words": ["remain"], "examples": []}]}, {"format": "ADV.", "groups": [{"words": ["completely", "entirely", "quite", "totally", "wholly"], "examples": []}, {"words": ["virtually"], "examples": []}, {"words": ["largely"], "examples": []}, {"words": ["temporarily"], "examples": []}, {"words": ["conspicuously", "markedly", "notably", "noticeably", "strikingly"], "examples": ["Local people were conspicuously absent from the meeting."]}, {"words": ["strangely"], "examples": ["He played with an abandon that was strangely absent from his performance last week."]}]}, {"format": "PREP.", "groups": [{"words": ["from"], "examples": ["He was absent from work for two weeks."]}]}]}], "link": []}