{"word": "avalanche", "type": "noun", "meanings": [{"meaning": "large amount of snow falling", "collocation": [{"format": "AVALANCHE + VERB", "groups": [{"words": ["happen", "strike sth"], "examples": ["The avalanche struck the ski resort in the late afternoon."]}, {"words": ["engulf sb/sth"], "examples": []}, {"words": ["kill sb"], "examples": ["They were killed by an avalanche in the Swiss Alps."]}]}, {"format": "PREP.", "groups": [{"words": ["in an/the ~"], "examples": ["They died in an avalanche."]}]}]}, {"meaning": "large number/amount of sth", "collocation": [{"format": "VERB + AVALANCHE", "groups": [{"words": ["be buried under"], "examples": []}]}, {"format": "AVALANCHE + VERB", "groups": [{"words": ["engulf sth"], "examples": ["the avalanche of lawlessness threatening to engulf our civilization"]}]}, {"format": "PREP.", "groups": [{"words": ["~ of"], "examples": ["We've been almost buried under the avalanche of mail."]}]}]}], "link": []}