{"word": "brochure", "type": "noun", "meanings": [{"meaning": "", "collocation": [{"format": "ADJ.", "groups": [{"words": ["(full) colour", "glossy"], "examples": []}, {"words": ["illustrated"], "examples": ["Send for our illustrated brochure."]}, {"words": ["holiday", "hotel", "travel"], "examples": []}]}, {"format": "QUANT.", "groups": [{"words": ["copy"], "examples": []}]}, {"format": "VERB + BROCHURE", "groups": [{"words": ["browse/leaf/look through"], "examples": ["I leafed through the travel brochure."]}, {"words": ["produce", "publish"], "examples": []}]}]}], "link": []}