{"word": "chocolate", "type": "noun", "meanings": [{"meaning": "sweet brown food", "collocation": [{"format": "ADJ.", "groups": [{"words": ["dark", "plain"], "examples": []}, {"words": ["milk"], "examples": []}, {"words": ["white"], "examples": []}, {"words": ["bitter"], "examples": []}, {"words": ["cooking"], "examples": []}]}, {"format": "QUANT.", "groups": [{"words": ["bar", "slab"], "examples": []}, {"words": ["bit", "piece", "square"], "examples": ["He broke off a few squares of chocolate."]}, {"words": ["box"], "examples": ["I gave her a box of hand-made Belgian chocolates."]}]}, {"format": "VERB + CHOCOLATE", "groups": [{"words": ["eat", "have"], "examples": []}, {"words": ["break (up) into pieces/squares"], "examples": ["She broke a bar of dark chocolate into four pieces."]}, {"words": ["grate"], "examples": []}, {"words": ["melt"], "examples": ["Melt 100g of cooking chocolate in a basin over hot water."]}, {"words": ["coat/cover sth in/with", "dip sth in", "spread/sprinkle (sth with)"], "examples": ["a box of brazil nuts coated in chocolate"]}]}, {"format": "CHOCOLATE + VERB", "groups": [{"words": ["melt"], "examples": ["Stir until the chocolate has melted."]}]}, {"format": "CHOCOLATE + NOUN", "groups": [{"words": ["bar", "chip"], "examples": []}, {"words": ["biscuit", "cake", "eclair", "egg", "gateau", "ice cream", "mousse", "sauce"], "examples": []}, {"words": ["factory"], "examples": []}]}]}, {"meaning": "small sweet made from chocolate", "collocation": [{"format": "ADJ.", "groups": [{"words": ["soft-centred"], "examples": []}, {"words": ["hand-made"], "examples": []}]}, {"format": "QUANT.", "groups": [{"words": ["box"], "examples": []}]}, {"format": "CHOCOLATE + NOUN", "groups": [{"words": ["box"], "examples": []}]}]}, {"meaning": "drink made from powdered chocolate", "collocation": [{"format": "ADJ.", "groups": [{"words": ["hot"], "examples": []}, {"words": ["drinking"], "examples": []}]}, {"format": "QUANT.", "groups": [{"words": ["cup", "mug"], "examples": []}]}]}], "link": []}