{"word": "contemplation", "type": "noun", "meanings": [{"meaning": "", "collocation": [{"format": "ADJ.", "groups": [{"words": ["quiet", "silent"], "examples": []}, {"words": ["deep"], "examples": []}]}, {"format": "VERB + CONTEMPLATION", "groups": [{"words": ["be deep in", "be lost in"], "examples": ["She was lost in contemplation of the scene in front of her."]}]}, {"format": "PREP.", "groups": [{"words": ["in ~ (of)"], "examples": ["He spent many hours in deep contemplation."]}, {"words": ["~ of"], "examples": ["the contemplation of beauty"]}]}]}], "link": []}