{"word": "convoy", "type": "noun", "meanings": [{"meaning": "", "collocation": [{"format": "ADJ.", "groups": [{"words": ["armed", "army", "military", "naval", "troop"], "examples": []}, {"words": ["road", "vehicle"], "examples": []}, {"words": ["aid", "food", "humanitarian", "relief"], "examples": ["the proposal to send 500 armed soldiers to escort food convoys"]}, {"words": ["UN/United Nations"], "examples": []}]}, {"format": "VERB + CONVOY", "groups": [{"words": ["lead"], "examples": []}, {"words": ["escort", "protect"], "examples": []}, {"words": ["attack"], "examples": []}]}, {"format": "CONVOY + VERB", "groups": [{"words": ["carry sth"], "examples": []}, {"words": ["arrive"], "examples": []}]}, {"format": "PREP.", "groups": [{"words": ["in ~"], "examples": ["The ships travelled in convoy."]}, {"words": ["~ of"], "examples": ["a large convoy of lorries carrying medical supplies"]}, {"words": ["~ to"], "examples": ["the next aid convoy to the war-torn region"]}]}]}], "link": []}