{"word": "crew", "type": "noun", "meanings": [{"meaning": "", "collocation": [{"format": "ADJ.", "groups": [{"words": ["experienced"], "examples": []}, {"words": ["inexperienced", "novice"], "examples": []}, {"words": ["emergency", "skeleton"], "examples": []}, {"words": ["aircraft", "bomber", "lifeboat", "ship's", "submarine", "tank", "train"], "examples": []}, {"words": ["cabin", "flight", "ground", "maintenance", "support"], "examples": []}, {"words": ["ambulance", "camera", "demolition", "film", "fire", "gun", "production", "road", "stage", "television", "TV"], "examples": ["Fire crews were called to the scene."]}]}, {"format": "CREW + NOUN", "groups": [{"words": ["member"], "examples": []}]}, {"format": "PREP.", "groups": [{"words": ["in a/the ~"], "examples": ["all the men and women in the crew"]}]}, {"format": "PHRASES", "groups": [{"words": ["a member of the crew"], "examples": []}]}]}], "link": []}