{"word": "cruel", "type": "adj.", "meanings": [{"meaning": "", "collocation": [{"format": "VERBS", "groups": [{"words": ["be", "seem", "sound"], "examples": []}, {"words": ["become"], "examples": []}]}, {"format": "ADV.", "groups": [{"words": ["extremely", "unspeakably", "very"], "examples": ["an extremely cruel regime"]}, {"words": ["a little", "rather"], "examples": []}, {"words": ["deliberately"], "examples": []}, {"words": ["unnecessarily"], "examples": []}]}, {"format": "PREP.", "groups": [{"words": ["to"], "examples": ["I can't stand people who are cruel to animals."]}]}]}], "link": []}