{"word": "dumb", "type": "adj.", "meanings": [{"meaning": "unable to speak", "collocation": [{"format": "VERBS", "groups": [{"words": ["be"], "examples": []}, {"words": ["become", "be struck"], "examples": ["They were struck dumb by some sort of shock."]}]}, {"format": "PREP.", "groups": [{"words": ["with"], "examples": ["She sat there, dumb with rage."]}]}, {"format": "PHRASES", "groups": [{"words": ["deaf and dumb"], "examples": []}]}]}, {"meaning": "stupid", "collocation": [{"format": "VERBS", "groups": [{"words": ["be", "feel", "look", "seem", "sound"], "examples": ["I'm sure my question sounded really dumb."]}, {"words": ["act", "play"], "examples": ["I decided to act dumb."]}]}, {"format": "ADV.", "groups": [{"words": ["really", "very"], "examples": []}, {"words": ["pretty", "rather"], "examples": []}]}]}], "link": []}