{"word": "faculty", "type": "noun", "meanings": [{"meaning": "natural ability of the body/mind", "collocation": [{"format": "ADJ.", "groups": [{"words": ["higher"], "examples": ["the evolution of man's higher faculties"]}, {"words": ["cognitive", "intellectual", "mental", "rational"], "examples": ["He is not in full possession of all his mental faculties."]}, {"words": ["creative", "critical", "imaginative", "moral"], "examples": []}, {"words": ["human"], "examples": []}]}, {"format": "VERB + FACULTY", "groups": [{"words": ["be in possession of", "have"], "examples": ["She is over eighty but still has all her faculties."]}, {"words": ["lose"], "examples": []}, {"words": ["develop"], "examples": ["trying to develop the student's critical faculties"]}]}, {"format": "PREP.", "groups": [{"words": ["~ for"], "examples": ["our faculty for picking up speech even in noisy environments"]}]}]}, {"meaning": "university department", "collocation": [{"format": "ADJ.", "groups": [{"words": ["Arts", "English", "law", "medical", "etc."], "examples": []}]}, {"format": "FACULTY + NOUN", "groups": [{"words": ["board", "head", "member"], "examples": []}]}, {"format": "PREP.", "groups": [{"words": ["across ~"], "examples": ["collaboration across faculties"]}, {"words": ["in a/the ~"], "examples": ["students who are doing degrees in the Arts Faculty"]}, {"words": ["~ of"], "examples": ["the Faculty of Arts"]}]}]}], "link": []}