{"word": "flushed", "type": "adj.", "meanings": [{"meaning": "", "collocation": [{"format": "VERBS", "groups": [{"words": ["appear", "be", "feel", "look"], "examples": []}, {"words": ["become"], "examples": []}]}, {"format": "ADV.", "groups": [{"words": ["deeply", "extremely", "very"], "examples": []}, {"words": ["a bit", "faintly", "a little", "quite", "slightly"], "examples": []}, {"words": ["unnaturally"], "examples": []}]}, {"format": "PREP.", "groups": [{"words": ["with"], "examples": ["Her face was flushed with embarrassment."]}]}]}], "link": []}