{"word": "furnished", "type": "adj.", "meanings": [{"meaning": "", "collocation": [{"format": "VERBS", "groups": [{"words": ["be"], "examples": []}]}, {"format": "ADV.", "groups": [{"words": ["fully"], "examples": ["The flat is fully furnished."]}, {"words": ["partially", "partly"], "examples": []}, {"words": ["attractively", "beautifully", "charmingly", "comfortably", "elegantly", "expensively", "luxuriously", "nicely", "ornately", "pleasantly", "prettily", "richly", "sumptuously", "tastefully", "well"], "examples": ["His rooms were comfortably furnished. The villa was expensively furnished throughout."]}, {"words": ["basically", "modestly", "plainly", "simply"], "examples": ["a simply furnished room"]}, {"words": ["adequately"], "examples": []}, {"words": ["barely", "sparsely"], "examples": []}, {"words": ["individually"], "examples": ["Each of the ten bedrooms is individually furnished."]}]}]}], "link": []}