{"word": "generalization", "type": "noun", "meanings": [{"meaning": "", "collocation": [{"format": "ADJ.", "groups": [{"words": ["broad", "sweeping"], "examples": []}, {"words": ["abstract"], "examples": []}, {"words": ["useful", "valid"], "examples": []}]}, {"format": "VERB + GENERALIZATION", "groups": [{"words": ["make"], "examples": []}]}, {"format": "PREP.", "groups": [{"words": ["~ about"], "examples": ["The author makes several sweeping generalizations about the causes of the crisis."]}]}]}], "link": []}