{"word": "grind", "type": "verb", "meanings": [{"meaning": "", "collocation": [{"format": "ADV.", "groups": [{"words": ["coarsely"], "examples": []}, {"words": ["finely"], "examples": ["The cement need not be finely ground."]}, {"words": ["down", "up"], "examples": ["Grind the seeds down to a powder."]}]}, {"format": "PREP.", "groups": [{"words": ["into"], "examples": ["machinery for grinding wheat into flour"]}, {"words": ["to"], "examples": ["The coffee is ground to a fine powder."]}]}, {"format": "PHRASES", "groups": [{"words": ["freshly ground"], "examples": ["freshly ground black pepper"]}]}]}], "link": []}