{"word": "grudge", "type": "noun", "meanings": [{"meaning": "", "collocation": [{"format": "ADJ.", "groups": [{"words": ["long-standing", "old"], "examples": ["It's time to forget old grudges."]}, {"words": ["personal"], "examples": []}]}, {"format": "VERB + GRUDGE", "groups": [{"words": ["bear", "harbour", "have", "hold", "nurse"], "examples": ["I don't hold grudges for very long."]}]}, {"format": "PREP.", "groups": [{"words": ["~ against"], "examples": ["Do you know anyone who might harbour a grudge against you?"]}]}]}], "link": []}