{"word": "honey", "type": "noun", "meanings": [{"meaning": "", "collocation": [{"format": "ADJ.", "groups": [{"words": ["clear"], "examples": []}, {"words": ["runny"], "examples": []}, {"words": ["wild"], "examples": []}]}, {"format": "QUANT.", "groups": [{"words": ["dollop"], "examples": []}, {"words": ["jar", "pot"], "examples": []}]}, {"format": "VERB + HONEY", "groups": [{"words": ["make", "produce"], "examples": ["learning how bees make honey a jar of locally-produced honey"]}, {"words": ["gather"], "examples": ["to gather honey from the hive"]}, {"words": ["spread (sth with)"], "examples": ["He spread some honey on his bread."]}]}, {"format": "HONEY + NOUN", "groups": [{"words": ["bee"], "examples": []}]}, {"format": "PHRASES", "groups": [{"words": ["as sweet as honey"], "examples": []}]}]}], "link": []}