{"word": "ice", "type": "noun", "meanings": [{"meaning": "", "collocation": [{"format": "ADJ.", "groups": [{"words": ["thick"], "examples": ["Is the ice thick enough to walk on?"]}, {"words": ["thin"], "examples": []}, {"words": ["black"], "examples": ["Motorists have been warned about black ice on the roads."]}]}, {"format": "QUANT.", "groups": [{"words": ["block", "slab"], "examples": ["The spray froze and formed great blocks of ice on the front of the ship."]}]}, {"format": "VERB + ICE", "groups": [{"words": ["form"], "examples": []}]}, {"format": "ICE + VERB", "groups": [{"words": ["form"], "examples": ["Ice had formed on the pond."]}, {"words": ["crack", "melt"], "examples": ["The ice was beginning to melt."]}]}, {"format": "PREP.", "groups": [{"words": ["on the ~"], "examples": ["skating on the ice"]}]}]}], "link": []}