{"word": "irritation", "type": "noun", "meanings": [{"meaning": "feeling/cause of being irritated", "collocation": [{"format": "ADJ.", "groups": [{"words": ["considerable", "great", "intense", "major", "serious", "some"], "examples": []}, {"words": ["growing", "increasing"], "examples": []}, {"words": ["mild", "minor", "slight"], "examples": ["the minor irritation of having to queue"]}, {"words": ["constant"], "examples": []}]}, {"format": "VERB + IRRITATION", "groups": [{"words": ["feel"], "examples": ["He felt slight irritation at being kept waiting."]}, {"words": ["express", "show"], "examples": ["He showed no irritation at the delay."]}, {"words": ["conceal", "hide", "suppress"], "examples": ["She made no attempt to conceal her irritation."]}, {"words": ["cause"], "examples": ["Such delays can cause considerable irritation."]}]}, {"format": "IRRITATION + VERB", "groups": [{"words": ["grow", "rise"], "examples": ["She felt irritation rising in her."]}, {"words": ["show"], "examples": ["She didn't let her irritation show."]}]}, {"format": "PREP.", "groups": [{"words": ["in ~"], "examples": ["Gary shook his head in irritation."]}, {"words": ["to your ~"], "examples": ["I found to my great irritation that I'd forgotten the film."]}, {"words": ["with ~"], "examples": ["\u2018Of course not\u2019 she said with some irritation."]}, {"words": ["~ at"], "examples": ["our irritation at the delay"]}, {"words": ["~ to"], "examples": ["This is a major irritation to travellers."]}, {"words": ["~ with"], "examples": ["her irritation with people who were slow"]}]}, {"format": "PHRASES", "groups": [{"words": ["a feeling/sense of irritation", "a source of irritation"], "examples": ["Traffic noise is a source of constant irritation."]}]}]}, {"meaning": "slight pain in part of the body", "collocation": [{"format": "ADJ.", "groups": [{"words": ["intense", "severe"], "examples": []}, {"words": ["mild"], "examples": []}, {"words": ["eye", "skin"], "examples": ["a new cream to treat skin irritation"]}]}, {"format": "VERB + IRRITATION", "groups": [{"words": ["cause", "lead to"], "examples": ["The infection can cause intense irritation of the throat."]}, {"words": ["experience", "get", "suffer"], "examples": ["Stop using the cream if you get any irritation."]}]}]}], "link": []}