{"word": "jaw", "type": "noun", "meanings": [{"meaning": "bone that contains teeth", "collocation": [{"format": "ADJ.", "groups": [{"words": ["bottom", "lower"], "examples": []}, {"words": ["top", "upper"], "examples": []}, {"words": ["firm", "strong"], "examples": []}, {"words": ["clenched", "set"], "examples": []}, {"words": ["slack"], "examples": []}, {"words": ["jutting", "lantern", "pointed", "square"], "examples": []}, {"words": ["broken", "dislocated", "fractured"], "examples": []}]}, {"format": "VERB + JAW", "groups": [{"words": ["clench", "set"], "examples": []}, {"words": ["finger", "rub", "stroke"], "examples": ["He fingered his jaw thoughtfully."]}, {"words": ["break", "dislocate", "fracture"], "examples": []}]}, {"format": "JAW + VERB", "groups": [{"words": ["drop", "sag"], "examples": ["My jaw dropped in astonishment when I saw the size of the audience."]}, {"words": ["be set", "clench", "set", "tighten"], "examples": ["Her jaw was set, ready for a fight."]}, {"words": ["jut"], "examples": ["His jaw jutted stubbornly forward; he would not be denied."]}]}, {"format": "JAW + NOUN", "groups": [{"words": ["bone", "muscle"], "examples": []}, {"words": ["injury"], "examples": []}]}, {"format": "PREP.", "groups": [{"words": ["in your ~"], "examples": ["A muscle in his jaw pulsed angrily."]}, {"words": ["on your ~"], "examples": ["He had two days' growth of stubble on his jaw."]}, {"words": ["to the ~"], "examples": ["a punch to the jaw"]}, {"words": ["under your ~"], "examples": ["She had a fold of flesh under her jaw."]}]}, {"format": "PHRASES", "groups": [{"words": ["the line/set of your jaw"], "examples": ["The stern set of the officer's jaw made Tony realize he was in trouble."]}]}]}, {"meaning": "jaws: mouth", "collocation": [{"format": "ADJ.", "groups": [{"words": ["gaping", "open"], "examples": []}, {"words": ["massive", "powerful"], "examples": ["A shark can crush a boat with its massive jaws."]}, {"words": ["slavering"], "examples": ["The slavering jaws of the guard dog stopped anyone going near."]}]}, {"format": "VERB + JAW", "groups": [{"words": ["clamp", "close", "lock", "sink"], "examples": ["The dog locked its jaws on her leg and wouldn't let go. A spider sank its jaws into my ankle."]}, {"words": ["escape (from)"], "examples": ["The antelope could not escape the crocodile's gaping jaws."]}]}, {"format": "PREP.", "groups": [{"words": ["between its ~s"], "examples": ["The dog had his arm clamped between its jaws."]}]}]}], "link": []}