{"word": "live", "type": "adj., adv.", "meanings": [{"meaning": "", "collocation": [{"format": "VERBS", "groups": [{"words": ["appear", "be", "play"], "examples": ["He appeared live on the Song and Dance Show. Is the show live or recorded? The band have never played this song live before."]}, {"words": ["come to sb", "go out"], "examples": ["This programme comes to you live from the Albert Hall. In those days the broadcasts all went out live."]}, {"words": ["be broadcast", "be screened", "be shown", "be televised", "be transmitted"], "examples": ["The match will be televised live this evening."]}, {"words": ["be recorded"], "examples": ["The CD was recorded live at a concert given last year."]}]}]}], "link": []}