{"word": "low-key", "type": "adj.", "meanings": [{"meaning": "", "collocation": [{"format": "VERBS", "groups": [{"words": ["be", "seem"], "examples": []}, {"words": ["keep sth"], "examples": ["We want to keep the whole affair as low-key as possible."]}]}, {"format": "ADV.", "groups": [{"words": ["extremely", "very"], "examples": ["The wedding was a very low-key affair."]}, {"words": ["fairly", "quite", "rather", "relatively"], "examples": ["We have a fairly low-key approach to discipline."]}, {"words": ["deliberately"], "examples": []}]}]}], "link": []}