{"word": "mess", "type": "noun", "meanings": [{"meaning": "", "collocation": [{"format": "ADJ.", "groups": [{"words": ["absolute", "complete", "real", "right", "total"], "examples": []}, {"words": ["appalling", "awful", "bloody", "confusing"], "examples": ["(taboo)"]}, {"words": ["tangled", "untidy"], "examples": ["Her hair was a tangled mess."]}, {"words": ["gooey", "slimy", "soggy", "sticky"], "examples": []}, {"words": ["emotional"], "examples": ["He's an emotional mess since his girlfriend left him."]}, {"words": ["economic", "financial"], "examples": []}]}, {"format": "VERB + MESS", "groups": [{"words": ["leave", "make"], "examples": ["Must you always leave such a mess? She felt she was making a terrible mess of her life."]}, {"words": ["clean up", "clear up", "tidy up", "wipe up"], "examples": []}, {"words": ["feel"], "examples": ["I felt a mess."]}, {"words": ["look"], "examples": []}, {"words": ["create", "get sb into"], "examples": ["Who got us into this mess in the first place?"]}, {"words": ["deal with", "get sb out of", "sort out"], "examples": []}]}, {"format": "PREP.", "groups": [{"words": ["in a ~"], "examples": ["The kitchen's in an awful mess."]}, {"words": ["~ of"], "examples": ["There was a soggy mess of porridge on the table."]}]}]}], "link": []}