{"word": "microphone", "type": "noun", "meanings": [{"meaning": "", "collocation": [{"format": "ADJ.", "groups": [{"words": ["extension", "radio", "stick", "tie-clip"], "examples": []}, {"words": ["built-in", "camcorder"], "examples": []}, {"words": ["omnidirectional", "unidirectional"], "examples": []}, {"words": ["hidden"], "examples": []}]}, {"format": "VERB + MICROPHONE", "groups": [{"words": ["speak into", "use"], "examples": []}, {"words": ["check", "test"], "examples": []}]}, {"format": "MICROPHONE + VERB", "groups": [{"words": ["pick sth up", "record sth"], "examples": ["the microphone picks up the surrounding sounds"]}]}, {"format": "MICROPHONE + NOUN", "groups": [{"words": ["socket"], "examples": []}, {"words": ["stand"], "examples": []}]}, {"format": "PREP.", "groups": [{"words": ["behind a/the ~"], "examples": ["John Peel is back behind the microphone for a new series."]}, {"words": ["in front of a/the ~"], "examples": ["Interviewees are placed in front of the microphone and grilled."]}]}]}], "link": []}