{"word": "notebook", "type": "noun", "meanings": [{"meaning": "", "collocation": [{"format": "ADJ.", "groups": [{"words": ["bound", "leather-bound", "spiral-bound"], "examples": []}, {"words": ["loose-leaf"], "examples": []}, {"words": ["pocket"], "examples": []}, {"words": ["shorthand"], "examples": []}, {"words": ["reporter's"], "examples": []}]}, {"format": "VERB + NOTEBOOK", "groups": [{"words": ["enter sth in", "jot sth down in", "record sth in", "scribble (sth) in", "write sth down in", "write (sth) in"], "examples": []}, {"words": ["draw (out)", "get out", "pull out", "take out"], "examples": ["She drew a notebook from her bag."]}, {"words": ["tear a page/sheet from", "tear out a page/sheet of"], "examples": []}, {"words": ["consult"], "examples": []}, {"words": ["fill"], "examples": []}, {"words": ["carry"], "examples": []}, {"words": ["keep"], "examples": ["She kept a notebook during the trip."]}]}, {"format": "NOTEBOOK + NOUN", "groups": [{"words": ["computer"], "examples": []}]}, {"format": "PREP.", "groups": [{"words": ["in a/your ~"], "examples": []}]}, {"format": "PHRASES", "groups": [{"words": ["an entry in a notebook"], "examples": []}]}]}], "link": []}