{"word": "old age", "type": "noun", "meanings": [{"meaning": "", "collocation": [{"format": "ADJ.", "groups": [{"words": ["advanced", "extreme"], "examples": []}, {"words": ["good"], "examples": ["He attained a good old age and died content."]}, {"words": ["happy"], "examples": ["She can look forward to a happy old age."]}, {"words": ["lonely"], "examples": ["fears about a lonely old age"]}]}, {"format": "VERB + OLD AGE", "groups": [{"words": ["attain", "live to", "reach", "survive into"], "examples": ["All my grandparents survived into advanced old age."]}, {"words": ["approach"], "examples": []}, {"words": ["look forward to"], "examples": []}, {"words": ["dread"], "examples": []}]}, {"format": "OLD AGE + NOUN", "groups": [{"words": ["pension", "pensioner"], "examples": []}]}, {"format": "PREP.", "groups": [{"words": ["in (your) ~"], "examples": ["Loss of hearing often occurs in old age. He took up golf in his old age."]}, {"words": ["into ~"], "examples": ["She was now well into old age."]}]}, {"format": "PHRASES", "groups": [{"words": ["the grand/ripe old age of sth"], "examples": ["She lived to the ripe old age of 98."]}]}]}], "link": []}