{"word": "pant", "type": "verb", "meanings": [{"meaning": "", "collocation": [{"format": "ADV.", "groups": [{"words": ["breathlessly"], "examples": []}, {"words": ["heavily", "loudly"], "examples": []}, {"words": ["slightly"], "examples": []}]}, {"format": "PREP.", "groups": [{"words": ["for"], "examples": ["He was panting for breath."]}, {"words": ["with"], "examples": ["She was panting with the effort of carrying the suitcase."]}]}, {"format": "PHRASES", "groups": [{"words": ["puff and pant"], "examples": ["Mason puffed and panted up the stairs."]}]}]}], "link": []}