{"word": "poisoning", "type": "noun", "meanings": [{"meaning": "", "collocation": [{"format": "ADJ.", "groups": [{"words": ["acute", "chronic"], "examples": []}, {"words": ["blood"], "examples": []}, {"words": ["food"], "examples": ["a bad case of food poisoning"]}, {"words": ["alcohol", "arsenic", "carbon monoxide", "lead", "mercury", "pesticide", "radiation", "etc."], "examples": []}]}, {"format": "QUANT.", "groups": [{"words": ["case"], "examples": []}]}, {"format": "VERB + POISONING", "groups": [{"words": ["die from/of"], "examples": []}]}]}], "link": []}