{"word": "prefer", "type": "verb", "meanings": [{"meaning": "", "collocation": [{"format": "ADV.", "groups": [{"words": ["greatly", "much", "strongly"], "examples": ["I much prefer the orchestra's 1998 recording of the symphony."]}, {"words": ["infinitely"], "examples": []}, {"words": ["simply"], "examples": ["You may simply prefer just to sit on the terrace with a cocktail."]}, {"words": ["really"], "examples": ["I would really prefer to teach girls."]}, {"words": ["rather", "slightly"], "examples": []}, {"words": ["certainly"], "examples": ["Egg pasta is certainly preferred by many chefs."]}, {"words": ["clearly", "obviously"], "examples": []}, {"words": ["apparently"], "examples": ["Huge majorities apparently prefer reducing unemployment to fighting inflation."]}, {"words": ["generally", "usually"], "examples": []}, {"words": ["naturally"], "examples": ["Employers naturally prefer candidates with some previous experience of the job."]}, {"words": ["personally"], "examples": []}, {"words": ["still"], "examples": []}]}, {"format": "VERB + PREFER", "groups": [{"words": ["would"], "examples": ["We can eat out if you like, but I would prefer to stay in."]}, {"words": ["tend to"], "examples": ["Industries still tend to prefer virgin raw materials to recycled ones."]}, {"words": ["seem to"], "examples": []}]}, {"format": "PREP.", "groups": [{"words": ["to"], "examples": ["I prefer his earlier paintings to his later ones."]}]}]}], "link": []}