{"word": "qualify", "type": "verb", "meanings": [{"meaning": "have/give sb the right to sth", "collocation": [{"format": "ADV.", "groups": [{"words": ["automatically"], "examples": []}]}, {"format": "PREP.", "groups": [{"words": ["for"], "examples": ["You will automatically qualify for a pension."]}]}, {"format": "PHRASES", "groups": [{"words": ["qualify on the grounds of sth"], "examples": ["people who qualify for the grant on the grounds of disability"]}]}]}, {"meaning": "for a sports competition", "collocation": [{"format": "ADV.", "groups": [{"words": ["easily"], "examples": []}, {"words": ["duly"], "examples": ["South Korea duly qualified for the finals when they beat Italy 6?1."]}]}, {"format": "VERB + QUALIFY", "groups": [{"words": ["fail to"], "examples": []}]}, {"format": "PREP.", "groups": [{"words": ["for"], "examples": ["England failed to qualify for the final."]}]}]}, {"meaning": "fit a description", "collocation": [{"format": "ADV.", "groups": [{"words": ["hardly"], "examples": []}]}, {"format": "PREP.", "groups": [{"words": ["as"], "examples": ["A three-week course hardly qualifies as sufficient training."]}]}]}], "link": []}