{"word": "relative", "type": "noun", "meanings": [{"meaning": "", "collocation": [{"format": "ADJ.", "groups": [{"words": ["close", "near"], "examples": ["The succession passed to the nearest surviving relative."]}, {"words": ["distant"], "examples": []}, {"words": ["blood", "family"], "examples": ["If you die without a will, only a husband, wife, children and blood relatives are entitled to inherit your property."]}, {"words": ["immediate"], "examples": ["The deceased's immediate relatives, her mother and father, will inherit her estate."]}, {"words": ["living", "surviving"], "examples": []}, {"words": ["elderly", "old"], "examples": []}, {"words": ["young"], "examples": []}, {"words": ["female", "male"], "examples": []}, {"words": ["poor"], "examples": ["(often figurative) He believes that interior design is the poor relative of", "architecture."]}, {"words": ["dependent"], "examples": []}, {"words": ["disabled", "ill", "sick"], "examples": []}, {"words": ["distressed", "grieving"], "examples": []}]}, {"format": "VERB + RELATIVE", "groups": [{"words": ["have"], "examples": ["I have no parents or close relatives."]}, {"words": ["lose"], "examples": ["an organization that helps people who have lost their relatives"]}, {"words": ["care for", "give support to", "help", "look after", "support"], "examples": ["She's looking after an elderly relative."]}, {"words": ["live with"], "examples": []}, {"words": ["stay with", "visit"], "examples": []}, {"words": ["trace"], "examples": ["The police are trying to trace the relatives of the deceased."]}, {"words": ["inform"], "examples": ["The names of the victims are being withheld until the relatives have been informed."]}]}, {"format": "PHRASES", "groups": [{"words": ["friends and/or relatives"], "examples": ["an intimate reception for close friends and relatives"]}, {"words": ["a relative by marriage"], "examples": []}]}]}], "link": []}