{"word": "resource", "type": "noun", "meanings": [{"meaning": "", "collocation": [{"format": "ADJ.", "groups": [{"words": ["considerable", "enormous", "large", "major", "substantial"], "examples": ["The library is an enormous resource for historians of medieval France."]}, {"words": ["important", "vital"], "examples": []}, {"words": ["adequate", "sufficient"], "examples": []}, {"words": ["limited", "meagre", "scarce"], "examples": []}, {"words": ["renewable", "sustainable", "unlimited"], "examples": []}, {"words": ["finite", "limited", "non-renewable"], "examples": []}, {"words": ["available"], "examples": []}, {"words": ["additional", "extra"], "examples": []}, {"words": ["invaluable", "useful", "valuable"], "examples": ["Time is your most valuable resource, especially in examinations."]}, {"words": ["untapped"], "examples": []}, {"words": ["natural"], "examples": []}, {"words": ["material", "physical"], "examples": []}, {"words": ["energy", "mineral", "oil", "water"], "examples": []}, {"words": ["capital", "economic", "financial"], "examples": ["The school has limited financial resources."]}, {"words": ["human", "staff"], "examples": []}, {"words": ["information", "learning", "library", "teaching"], "examples": ["The database could be used as a teaching resource in colleges."]}, {"words": ["national"], "examples": []}, {"words": ["inner", "personal"], "examples": ["She is someone of considerable personal resources."]}]}, {"format": "VERB + RESOURCE", "groups": [{"words": ["be rich in", "have"], "examples": ["Australia is a country rich in natural resources. We do not have the resources", "to update our computer software."]}, {"words": ["lack"], "examples": []}, {"words": ["pool", "share"], "examples": ["We'll get by if we pool our resources."]}, {"words": ["allocate", "distribute", "provide"], "examples": []}, {"words": ["divert", "reallocate", "redistribute"], "examples": ["the government's role in diverting resources into social policies"]}, {"words": ["draw on", "exploit", "manage", "mobilize", "tap", "use"], "examples": ["to mobilize resources in the community to provide shelter for the homeless We need to manage our resources better."]}, {"words": ["deplete", "use up"], "examples": []}, {"words": ["squander", "waste"], "examples": []}, {"words": ["conserve"], "examples": []}]}, {"format": "RESOURCE + NOUN", "groups": [{"words": ["centre"], "examples": []}, {"words": ["allocation", "management"], "examples": []}, {"words": ["depletion"], "examples": []}, {"words": ["constraints", "implications"], "examples": []}]}, {"format": "PHRASES", "groups": [{"words": ["access to resources", "the allocation/distribution/provision of resources", "the exploitation of resources", "a lack of resources", "the use of resources"], "examples": ["We must make the most efficient use of the available resources."]}]}]}], "link": []}