{"word": "responsibility", "type": "noun", "meanings": [{"meaning": "being responsible", "collocation": [{"format": "ADJ.", "groups": [{"words": ["full", "total"], "examples": []}, {"words": ["awesome", "great", "heavy", "weighty"], "examples": ["It is a great responsibility looking after other people's children."]}, {"words": ["direct"], "examples": []}, {"words": ["overall"], "examples": []}, {"words": ["primary"], "examples": []}, {"words": ["ultimate"], "examples": ["Ultimate responsibility rests with the prime minister."]}, {"words": ["special"], "examples": []}, {"words": ["diminished"], "examples": ["He was found not guilty of murder on the grounds of diminished responsibility."]}, {"words": ["sole"], "examples": []}, {"words": ["collective", "joint", "shared"], "examples": []}, {"words": ["individual", "personal"], "examples": []}, {"words": ["ministerial", "parental"], "examples": []}, {"words": ["financial", "legal", "moral", "social"], "examples": []}]}, {"format": "VERB + RESPONSIBILITY", "groups": [{"words": ["have"], "examples": ["She has responsibility for public transport."]}, {"words": ["accept", "assume", "bear", "shoulder", "take (on/over)"], "examples": ["The bank refuses to accept responsibility for the mistake. Will you take responsibility for arranging the food?"]}, {"words": ["share"], "examples": []}, {"words": ["lay", "place"], "examples": ["The government of the time placed responsibility for the poor on the Church."]}, {"words": ["delegate", "devolve", "hand over"], "examples": ["devolving responsibility downwards so decisions are taken nearer to the people they will affect"]}, {"words": ["abdicate", "evade", "shirk", "shift"], "examples": ["to shift legal responsibility for the correct labelling of goods onto the shopkeeper"]}, {"words": ["admit", "claim"], "examples": ["No organization has yet claimed responsibility for the bomb attack."]}, {"words": ["deny", "disclaim", "duck"], "examples": ["Ducking responsibility is fatal in a democracy."]}, {"words": ["allocate", "assign (sb)", "give sb"], "examples": []}, {"words": ["attribute"], "examples": ["He attributed responsibility for the killing to the secret service."]}, {"words": ["burden sb with"], "examples": []}, {"words": ["absolve sb from/of"], "examples": []}]}, {"format": "RESPONSIBILITY + VERB", "groups": [{"words": ["fall on sb", "lie/rest with sb"], "examples": []}]}, {"format": "PREP.", "groups": [{"words": ["~ for"], "examples": ["Full responsibility for the fiasco lies with the PR department."]}, {"words": ["~ towards"], "examples": ["He feels a strong sense of responsibility towards his parents."]}]}, {"format": "PHRASES", "groups": [{"words": ["the age of criminal responsibility", "the burden of responsibility"], "examples": ["The school governors carry a special burden of responsibility."]}]}]}, {"meaning": "job/duty", "collocation": [{"format": "ADJ.", "groups": [{"words": ["heavy", "onerous"], "examples": []}, {"words": ["additional", "increased"], "examples": []}, {"words": ["altered"], "examples": []}, {"words": ["caring", "departmental", "domestic", "family", "financial", "managerial", "ministerial", "parental", "professional", "teaching"], "examples": []}, {"words": ["contractual", "statutory"], "examples": []}, {"words": ["particular", "special"], "examples": []}]}, {"format": "VERB + RESPONSIBILITY", "groups": [{"words": ["have"], "examples": []}, {"words": ["carry out", "discharge", "fulfil"], "examples": []}, {"words": ["accept", "face up to", "take on", "undertake"], "examples": ["He seems unwilling to face up to his responsibilities as a father. I don't feel ready to take on new responsibilities."]}, {"words": ["delegate"], "examples": []}, {"words": ["avoid", "evade", "shirk"], "examples": []}, {"words": ["relieve sb of"], "examples": []}]}, {"format": "PREP.", "groups": [{"words": ["~ for"], "examples": ["The heads of school departments have particular responsibilities for the curriculum."]}, {"words": ["~ to/towards"], "examples": ["The club has a responsibility to its members."]}]}, {"format": "PHRASES", "groups": [{"words": ["duties and responsibilities", "rights and responsibilities"], "examples": ["parental rights and responsibilities"]}]}]}], "link": []}