{"word": "sail", "type": "noun", "meanings": [{"meaning": "", "collocation": [{"format": "ADJ.", "groups": [{"words": ["main"], "examples": []}, {"words": ["canvas"], "examples": []}]}, {"format": "VERB + SAIL", "groups": [{"words": ["hoist", "raise"], "examples": []}, {"words": ["drop", "lower"], "examples": []}, {"words": ["adjust", "trim"], "examples": []}, {"words": ["fill"], "examples": ["The dinghy gathered speed as the wind filled her sails."]}, {"words": ["reef", "shorten"], "examples": []}, {"words": ["furl"], "examples": []}]}, {"format": "SAIL + VERB", "groups": [{"words": ["billow", "flap"], "examples": ["The bay was full of yachts with billowing sails."]}, {"words": ["fill"], "examples": []}]}, {"format": "SAIL + NOUN", "groups": [{"words": ["area", "shape", "size"], "examples": []}, {"words": ["canvas"], "examples": []}]}, {"format": "PREP.", "groups": [{"words": ["under ~"], "examples": ["The yacht came in under sail and anchored near us."]}]}, {"format": "PHRASES", "groups": [{"words": ["the days of sail"], "examples": ["The boat is preserved as a monument to the days of sail."]}, {"words": ["in/under full sail"], "examples": ["She advanced towards us like a galleon in full sail."]}, {"words": ["set sail (for)"], "examples": ["We set sail for France at first light."]}]}]}], "link": []}