{"word": "seniority", "type": "noun", "meanings": [{"meaning": "", "collocation": [{"format": "VERB + SENIORITY", "groups": [{"words": ["attain", "gain"], "examples": []}]}, {"format": "PREP.", "groups": [{"words": ["by ~"], "examples": ["Promotion in the job was by seniority."]}]}, {"format": "PHRASES", "groups": [{"words": ["in order of seniority", "a level of seniority", "next in seniority"], "examples": ["On the death of the captain, the officer next in seniority assumed command."]}]}]}], "link": []}