{"word": "tension", "type": "noun", "meanings": [{"meaning": "inability to relax", "collocation": [{"format": "ADJ.", "groups": [{"words": ["inner"], "examples": []}, {"words": ["emotional", "muscle/muscular", "nervous", "pre-menstrual", "sexual"], "examples": ["He suffers from nervous tension."]}]}, {"format": "VERB + TENSION", "groups": [{"words": ["feel", "suffer from"], "examples": ["I feel some tension in my shoulders."]}, {"words": ["sense"], "examples": ["As soon as he entered, he sensed a tension in the air."]}, {"words": ["cause", "create"], "examples": []}, {"words": ["relieve"], "examples": []}, {"words": ["release"], "examples": []}]}, {"format": "TENSION + NOUN", "groups": [{"words": ["headache"], "examples": []}]}, {"format": "PREP.", "groups": [{"words": ["~ in"], "examples": ["The hot bath eased the tension in his body."]}]}, {"format": "PHRASES", "groups": [{"words": ["a release of tension"], "examples": ["Laughter can be a great release of tension."]}, {"words": ["a sign of tension"], "examples": ["Horses are very sensitive to signs of tension in humans."]}]}]}, {"meaning": "bad feeling between people, countries, etc.", "collocation": [{"format": "ADJ.", "groups": [{"words": ["considerable", "great", "high"], "examples": ["More police have been sent to areas of high political tension."]}, {"words": ["slight"], "examples": []}, {"words": ["growing", "heightened", "increased", "increasing", "mounting"], "examples": []}, {"words": ["constant"], "examples": []}, {"words": ["unresolved"], "examples": []}, {"words": ["renewed"], "examples": []}, {"words": ["ethnic", "political", "racial", "religious", "social"], "examples": []}, {"words": ["communal", "family", "internal", "international", "national", "regional"], "examples": []}]}, {"format": "VERB + TENSION", "groups": [{"words": ["cause", "create", "generate"], "examples": []}, {"words": ["defuse", "ease", "reduce"], "examples": ["She often used humour to defuse tension in meetings."]}, {"words": ["heighten"], "examples": []}]}, {"format": "TENSION + VERB", "groups": [{"words": ["build up", "grow", "increase", "mount", "rise"], "examples": []}, {"words": ["ease"], "examples": []}, {"words": ["be palpable"], "examples": []}]}, {"format": "PREP.", "groups": [{"words": ["~ among"], "examples": ["The tension among the audience was palpable."]}, {"words": ["~ between"], "examples": ["tension between local youths and the police"]}, {"words": ["~ in/within"], "examples": ["The redundancies caused greater tensions within the company."]}, {"words": ["~ over"], "examples": ["There has been increased tension over the border incident."]}, {"words": ["~ with"], "examples": ["renewed tension with France"]}]}, {"format": "PHRASES", "groups": [{"words": ["a source of tension"], "examples": ["Money was always a source of tension between her parents."]}]}]}, {"meaning": "of rope, wire, etc.", "collocation": [{"format": "ADJ.", "groups": [{"words": ["string"], "examples": []}]}, {"format": "VERB + TENSION", "groups": [{"words": ["adjust"], "examples": ["This ol", "racket needs its string tension adjusted."]}, {"words": ["release"], "examples": []}]}, {"format": "PREP.", "groups": [{"words": ["in ~"], "examples": ["The metal is weak in tension."]}, {"words": ["under ~"], "examples": ["Stay clear of cables which are under tension."]}, {"words": ["~ on"], "examples": ["The sudden tension on the line told me I had hooked a fish."]}]}]}], "link": []}