{"word": "tough", "type": "adj.", "meanings": [{"meaning": "difficult/unpleasant", "collocation": [{"format": "VERBS", "groups": [{"words": ["be", "seem"], "examples": []}, {"words": ["get"], "examples": []}]}, {"format": "ADV.", "groups": [{"words": ["extremely", "particularly", "really", "very"], "examples": []}, {"words": ["a bit", "fairly", "a little", "pretty", "quite"], "examples": ["Things were pretty tough at first."]}]}, {"format": "PREP.", "groups": [{"words": ["on"], "examples": ["It's very tough on the wives when the husbands go off like that."]}]}]}, {"meaning": "strict/firm", "collocation": [{"format": "VERBS", "groups": [{"words": ["be"], "examples": []}, {"words": ["become", "get"], "examples": []}]}, {"format": "ADV.", "groups": [{"words": ["extremely", "particularly", "very"], "examples": []}, {"words": ["fairly", "pretty", "quite"], "examples": []}, {"words": ["enough"], "examples": ["Has the government been tough enough on polluters?"]}]}, {"format": "PREP.", "groups": [{"words": ["on"], "examples": ["The government has promised to get tough on crime."]}, {"words": ["with"], "examples": ["You have to be tough with these young thugs."]}]}]}, {"meaning": "strong", "collocation": [{"format": "VERBS", "groups": [{"words": ["be", "feel", "look", "seem"], "examples": []}, {"words": ["become", "get", "grow"], "examples": []}, {"words": ["act", "talk"], "examples": ["(both informal) Then this guy started acting tough."]}]}, {"format": "ADV.", "groups": [{"words": ["incredibly", "really", "remarkably", "very"], "examples": []}, {"words": ["pretty", "quite", "reasonably"], "examples": []}, {"words": ["enough"], "examples": ["Are you sure you're physically tough enough for this job?"]}, {"words": ["mentally", "physically"], "examples": []}]}]}], "link": []}