{"word": "trade", "type": "noun", "meanings": [{"meaning": "buying/selling of goods/services", "collocation": [{"format": "ADJ.", "groups": [{"words": ["brisk", "flourishing", "lively", "roaring", "thriving"], "examples": ["All around the pyramids, salespeople were doing a roaring trade in souvenirs."]}, {"words": ["lucrative", "profitable"], "examples": []}, {"words": ["external", "foreign", "global", "international", "overseas", "world"], "examples": []}, {"words": ["domestic", "internal", "inter-provincial", "inter-regional", "regional"], "examples": []}, {"words": ["export", "import", "import-export"], "examples": []}, {"words": ["direct", "indirect"], "examples": []}, {"words": ["free"], "examples": []}, {"words": ["fair"], "examples": ["The organization promotes fair trade with developing countries."]}, {"words": ["legal", "legitimate"], "examples": []}, {"words": ["illegal", "illicit"], "examples": ["attempts to curb the illicit trade in exotic species"]}, {"words": ["private"], "examples": []}, {"words": ["bilateral", "mutual"], "examples": []}, {"words": ["unilateral"], "examples": []}, {"words": ["coastal", "maritime"], "examples": []}, {"words": ["agricultural", "commercial"], "examples": []}, {"words": ["retail", "wholesale"], "examples": ["It has been a bad year for the retail trade."]}, {"words": ["book", "fur", "slave", "timber", "tourist", "wine", "wool"], "examples": []}, {"words": ["evil"], "examples": ["the evil trade in drugs"]}]}, {"format": "VERB + TRADE", "groups": [{"words": ["carry on", "conduct", "do", "engage in", "ply"], "examples": ["the tools needed to carry on a trade All manner of hawkers and street sellers were plying their trade."]}, {"words": ["boost", "build up", "develop", "expand", "increase", "promote"], "examples": ["a bid to boost foreign trade He built up a trade in seeds, corn and manure."]}, {"words": ["damage", "harm"], "examples": ["A bitterly cold winter damaged industrial output and trade."]}, {"words": ["lose"], "examples": ["Shops have lost a day's trade."]}, {"words": ["ban", "restrict"], "examples": []}]}, {"format": "TRADE + VERB", "groups": [{"words": ["boom", "expand", "grow", "increase", "pick up"], "examples": []}, {"words": ["decline", "fall"], "examples": []}]}, {"format": "TRADE + NOUN", "groups": [{"words": ["balance", "figures", "performance", "statistics"], "examples": []}, {"words": ["surplus"], "examples": []}, {"words": ["deficit", "gap", "imbalance"], "examples": []}, {"words": ["barrier", "blockade", "boycott", "embargo", "restrictions", "sanctions"], "examples": []}, {"words": ["tariff"], "examples": []}, {"words": ["dispute", "war"], "examples": ["The countries were locked in a trade war, refusing to allow imports of each other's goods."]}, {"words": ["liberalization"], "examples": []}, {"words": ["benefits", "concessions"], "examples": []}, {"words": ["accord", "agreement", "deal", "pact", "protocol", "treaty"], "examples": []}, {"words": ["negotiations", "talks"], "examples": []}, {"words": ["cooperation", "links", "network", "relations"], "examples": []}, {"words": ["policy", "practice"], "examples": ["The US was accused of employing unfair trade practices."]}, {"words": ["law", "rules"], "examples": []}, {"words": ["bloc"], "examples": ["The five countries formed a regional trade bloc."]}, {"words": ["delegation", "mission"], "examples": ["Several local firms took part in a trade mission to Spain."]}, {"words": ["official", "representative", "exhibition", "fair", "show"], "examples": ["talks between trade officials from the two countries"]}, {"words": ["centre"], "examples": []}, {"words": ["route"], "examples": ["The road has been an important trade route since prehistoric times."]}, {"words": ["cycle"], "examples": ["the boom and slump periods of a trade cycle"]}, {"words": ["buyer", "customer"], "examples": ["The vase was bought by a trade buyer", "."]}, {"words": ["directory"], "examples": []}, {"words": ["journal", "magazine", "paper", "press"], "examples": []}, {"words": ["information", "secret"], "examples": ["The employees were fired for divulging trade secrets to a competitor."]}]}, {"format": "PREP.", "groups": [{"words": ["in a/the ~"], "examples": ["She's in the wholesale fruit trade. These special flour sacks are known in the trade as \u2018pockets\u2019."]}, {"words": ["~ between"], "examples": ["Trade between the Adriatic ports and their hinterland had grown."]}, {"words": ["~ in"], "examples": ["Steps were taken to ban the trade in ivory."]}, {"words": ["~ with"], "examples": ["The US has restricted trade with India."]}]}]}, {"meaning": "job", "collocation": [{"format": "VERB + TRADE", "groups": [{"words": ["learn"], "examples": []}, {"words": ["exercise", "follow", "practise"], "examples": []}]}, {"format": "PREP.", "groups": [{"words": ["by ~"], "examples": ["She is a carpenter by trade."]}]}, {"format": "PHRASES", "groups": [{"words": ["a jack of all trades"], "examples": ["The experienced artisan would pass on the tricks of the trade to the apprentice."]}]}]}], "link": []}