{"word": "trap", "type": "noun", "meanings": [{"meaning": "hidden equipment used for catching sb/sth", "collocation": [{"format": "ADJ.", "groups": [{"words": ["animal", "bear", "man", "mouse", "gin", "leghold", "pit/pitfall"], "examples": []}, {"words": ["radar", "speed"], "examples": ["Slow down?there are speed traps along this stretch of road."]}]}, {"format": "VERB + TRAP", "groups": [{"words": ["be/get caught in"], "examples": []}, {"words": ["catch sth in"], "examples": []}, {"words": ["free sth from"], "examples": ["The fox had managed to free itself from the trap."]}, {"words": ["lay", "set"], "examples": []}, {"words": ["bait"], "examples": ["Mousetraps are traditionally baited with cheese."]}]}]}, {"meaning": "sth that tricks you; unpleasant situation", "collocation": [{"format": "ADJ.", "groups": [{"words": ["hidden", "obvious"], "examples": []}, {"words": ["potential"], "examples": []}, {"words": ["booby"], "examples": []}, {"words": ["deadly"], "examples": []}, {"words": ["death", "debt", "poverty", "unemployment"], "examples": ["The overhead cable is a potential death trap for birds."]}, {"words": ["offside (in football)"], "examples": []}]}, {"format": "VERB + TRAP", "groups": [{"words": ["lay", "set"], "examples": []}, {"words": ["spring"], "examples": []}, {"words": ["lure sb into"], "examples": []}, {"words": ["catch sb in"], "examples": []}, {"words": ["be/get caught in", "fall into", "stumble into", "walk into"], "examples": ["It is easy to fall into the trap of taking out a loan you cannot afford."]}, {"words": ["avoid"], "examples": []}, {"words": ["fear", "suspect"], "examples": []}]}]}], "link": []}