{"word": "uncomfortable", "type": "adj.", "meanings": [{"meaning": "not comfortable", "collocation": [{"format": "VERBS", "groups": [{"words": ["be", "feel", "look", "seem"], "examples": []}, {"words": ["become", "get"], "examples": []}, {"words": ["make sth"], "examples": ["Sharp stones on the path made walking barefoot rather uncomfortable."]}, {"words": ["find sth"], "examples": ["I find these chairs incredibly uncomfortable."]}]}, {"format": "ADV.", "groups": [{"words": ["downright", "extremely", "incredibly", "most", "really", "terribly", "very"], "examples": []}, {"words": ["increasingly"], "examples": []}, {"words": ["a bit", "a little", "pretty", "quite", "rather"], "examples": []}, {"words": ["physically"], "examples": []}]}]}, {"meaning": "feeling/causing worry/embarrassment", "collocation": [{"format": "VERBS", "groups": [{"words": ["appear", "be", "feel", "look", "seem"], "examples": []}, {"words": ["become", "get"], "examples": ["He started to get a bit uncomfortable as the conversation continued."]}, {"words": ["make sb"], "examples": ["The way he looked at her made her distinctly uncomfortable."]}, {"words": ["find sth"], "examples": []}]}, {"format": "ADV.", "groups": [{"words": ["acutely", "decidedly", "deeply", "distinctly", "downright", "extremely", "really", "terribly", "very"], "examples": []}, {"words": ["increasingly"], "examples": []}, {"words": ["a bit", "a little", "rather", "slightly"], "examples": []}, {"words": ["clearly", "obviously", "visibly"], "examples": []}]}, {"format": "PREP.", "groups": [{"words": ["with"], "examples": ["Planners seem a little uncomfortable with the current government guidelines."]}]}]}], "link": []}