{"word": "veer", "type": "verb", "meanings": [{"meaning": "", "collocation": [{"format": "ADV.", "groups": [{"words": ["sharply", "violently", "wildly"], "examples": ["The ship veered round wildly in the rough sea."]}, {"words": ["(to the) left", "(to the) right"], "examples": []}, {"words": ["away", "round"], "examples": ["The plane veered away to the left."]}]}, {"format": "PREP.", "groups": [{"words": ["between"], "examples": ["(figurative) He veered between calm acceptance and hysterical accusations."]}, {"words": ["from"], "examples": ["(figurative) The play veers from loopy comedy to serious moralizing."]}, {"words": ["off"], "examples": ["The car veered off the road."]}, {"words": ["to"], "examples": ["The path veers sharply to the right."]}, {"words": ["towards"], "examples": ["He veered left towards them."]}]}]}], "link": []}