{"word": "vicious", "type": "adj.", "meanings": [{"meaning": "", "collocation": [{"format": "VERBS", "groups": [{"words": ["be", "look", "sound"], "examples": []}, {"words": ["become", "get", "turn"], "examples": ["The computer wars are going to get vicious over the next few years."]}]}, {"format": "ADV.", "groups": [{"words": ["particularly", "truly", "very"], "examples": ["a particularly vicious and brutal crime"]}, {"words": ["increasingly"], "examples": []}, {"words": ["rather"], "examples": []}]}]}], "link": []}