{"word": "want", "type": "noun", "meanings": [{"meaning": "", "collocation": [{"format": "ADJ.", "groups": [{"words": ["human"], "examples": []}]}, {"format": "VERB + WANT", "groups": [{"words": ["meet", "satisfy", "see to"], "examples": ["a society that satisfied all human wants"]}]}, {"format": "PREP.", "groups": [{"words": ["for ~ of"], "examples": ["Refugees are dying for want of proper health care."]}, {"words": ["in ~"], "examples": ["Thousands of children are living in want."]}]}]}], "link": []}