{"word": "week", "type": "noun", "meanings": [{"meaning": "", "collocation": [{"format": "ADJ.", "groups": [{"words": ["last", "past"], "examples": []}, {"words": ["previous"], "examples": []}, {"words": ["coming", "following", "next"], "examples": []}, {"words": ["consecutive", "successive"], "examples": ["They won 1?0 for the fourth consecutive week."]}, {"words": ["entire", "full", "whole"], "examples": ["It's the first time for ages I've done a full week's work."]}, {"words": ["working"], "examples": []}, {"words": ["busy", "hard"], "examples": []}, {"words": ["quiet"], "examples": ["It's been a very quiet week for me."]}, {"words": ["3-day", "40-hour", "etc."], "examples": ["He earns enough money to work a four-day week."]}]}, {"format": "VERB + WEEK", "groups": [{"words": ["spend"], "examples": ["We spent two weeks in France last summer."]}, {"words": ["take"], "examples": []}]}, {"format": "WEEK + VERB", "groups": [{"words": ["elapse", "go by", "pass"], "examples": ["The week passed very slowly."]}]}, {"format": "PREP.", "groups": [{"words": ["by the ~"], "examples": ["They're paid by the week."]}, {"words": ["during/in the ~"], "examples": ["I go out most weekends, but rarely during the week."]}, {"words": ["for a ~"], "examples": ["I haven't seen him for weeks."]}, {"words": ["in a ~"], "examples": ["We'll be back in a week."]}, {"words": ["in ~s"], "examples": ["It hasn't rained in weeks."]}, {"words": ["over/under a ~"], "examples": ["It's over a week since she rang me."]}, {"words": ["per ~"], "examples": ["How much do you earn per week?"]}, {"words": ["within a/the ~"], "examples": ["I'll have the report finished within the next couple of weeks."]}]}, {"format": "PHRASES", "groups": [{"words": ["a day of the week"], "examples": ["Which day of the week was it?"]}]}]}], "link": []}