{"word": "wildlife", "type": "noun", "meanings": [{"meaning": "", "collocation": [{"format": "ADJ.", "groups": [{"words": ["abundant"], "examples": []}, {"words": ["endangered", "rare"], "examples": []}, {"words": ["indigenous", "local", "native"], "examples": []}, {"words": ["marine", "urban", "wetland"], "examples": []}]}, {"format": "VERB + WILDLIFE", "groups": [{"words": ["preserve", "protect", "save"], "examples": ["They called on the government to help protect native wildlife."]}, {"words": ["attract", "encourage"], "examples": ["The large variety of native plants attracts wildlife to the area."]}, {"words": ["benefit"], "examples": []}, {"words": ["endanger", "threaten"], "examples": ["The increasing use of pesticides threatens the wildlife of the area."]}, {"words": ["damage", "harm"], "examples": []}, {"words": ["disturb"], "examples": ["Do not allow your dog to disturb wildlife."]}, {"words": ["be (a) home for/to", "be rich in"], "examples": ["The forest is home to a wealth of wildlife."]}]}, {"format": "WILDLIFE + NOUN", "groups": [{"words": ["habitat"], "examples": []}, {"words": ["area", "garden", "haven", "park", "refuge", "reserve", "sanctuary", "site"], "examples": ["The school has its own small wildlife garden."]}, {"words": ["conservation", "management", "protection"], "examples": []}, {"words": ["trade"], "examples": ["the illegal wildlife trade"]}, {"words": ["artist", "cameraman", "film-maker", "photographer"], "examples": []}]}, {"format": "PHRASES", "groups": [{"words": ["a wealth of wildlife"], "examples": []}]}]}], "link": []}