{"word": "wince", "type": "verb", "meanings": [{"meaning": "", "collocation": [{"format": "ADV.", "groups": [{"words": ["a little", "slightly"], "examples": []}, {"words": ["inwardly"], "examples": ["He winced inwardly at her harsh tone."]}, {"words": ["visibly"], "examples": []}]}, {"format": "VERB + WINCE", "groups": [{"words": ["try not to"], "examples": []}, {"words": ["make sb"], "examples": []}, {"words": ["see sb"], "examples": []}]}, {"format": "PREP.", "groups": [{"words": ["at"], "examples": ["She switched on the light, wincing at the sudden brightness."]}, {"words": ["in/with"], "examples": ["He winced in pain."]}]}]}], "link": []}